{
  "unversionedId": "api/batch",
  "id": "version-7.0/api/batch",
  "isDocsHomePage": false,
  "title": "batch",
  "description": "batch()",
  "source": "@site/versioned_docs\\version-7.0\\api\\batch.md",
  "slug": "/api/batch",
  "permalink": "/7.0/api/batch",
  "version": "7.0",
  "sidebar_label": "batch()",
  "sidebar": "version-7.0/docs",
  "previous": {
    "title": "connectAdvanced",
    "permalink": "/7.0/api/connect-advanced"
  },
  "next": {
    "title": "Troubleshooting",
    "permalink": "/7.0/troubleshooting"
  }
}